[
  {
    "sha": "480cfd95c6b96e564de35eb5a299c7c692d48651",
    "author": "RashLop",
    "commit": {
      "date": "2025-08-21T15:45:43.000Z",
      "message": "feat: funcion de hola agregado",
      "url": "https://github.com/RashLop/ChatBot/commit/480cfd95c6b96e564de35eb5a299c7c692d48651"
    },
    "stats": {
      "total": 5,
      "additions": 3,
      "deletions": 2,
      "date": "2025-08-21"
    },
    "coverage": 100,
    "test_count": 1,
    "failed_tests": 0,
    "conclusion": "success"
  },
  {
    "sha": "8279268dff55ece96b99c8fd7c4650a59a8dff16",
    "author": "RashLop",
    "commit": {
      "date": "2025-08-25T18:14:46.000Z",
      "message": "feat: Hola con nombre añadido",
      "url": "https://github.com/RashLop/ChatBot/commit/8279268dff55ece96b99c8fd7c4650a59a8dff16"
    },
    "stats": {
      "total": 30,
      "additions": 12,
      "deletions": 18,
      "date": "2025-08-25"
    },
    "coverage": 100,
    "test_count": 1,
    "failed_tests": 0,
    "conclusion": "success"
  },
  {
    "sha": "1245d938a8ef0e49d7cb512e0e05d543eea4e647",
    "author": "RashLop",
    "commit": {
      "date": "2025-08-25T18:24:57.000Z",
      "message": "feat: Saludar con la hora añadido",
      "url": "https://github.com/RashLop/ChatBot/commit/1245d938a8ef0e49d7cb512e0e05d543eea4e647"
    },
    "stats": {
      "total": 13,
      "additions": 11,
      "deletions": 2,
      "date": "2025-08-25"
    },
    "coverage": 100,
    "test_count": 1,
    "failed_tests": 0,
    "conclusion": "success"
  },
  {
    "sha": "HEAD",
    "author": "RashLop",
    "commit": {
      "date": "2025-08-25T18:37:11.000Z",
      "message": "feat: Saludar por genero añadido",
      "url": "https://github.com/RashLop/ChatBot/commit/HEAD"
    },
    "stats": {
      "total": 45,
      "additions": 32,
      "deletions": 13,
      "date": "2025-08-25"
    },
    "coverage": 100,
    "test_count": 1,
    "failed_tests": 0,
    "conclusion": "success"
  }
]